cloudViewer-0.3.7.data/data/etc/jupyter/nbconfig/notebook.d/enable_jupyter_extension.json
cloudViewer-0.3.7.data/data/share/jupyter/nbextensions/cloudViewer/12c8482249da928cedbafe8c3d624c0b.png
cloudViewer-0.3.7.data/data/share/jupyter/nbextensions/cloudViewer/extension.js
cloudViewer-0.3.7.data/data/share/jupyter/nbextensions/cloudViewer/index.js
cloudViewer-0.3.7.data/data/share/jupyter/nbextensions/cloudViewer/index.js.map
cloudViewer-0.3.7.data/purelib/cloudViewer/__init__.py
cloudViewer-0.3.7.data/purelib/cloudViewer/_build_config.py
cloudViewer-0.3.7.data/purelib/cloudViewer/core.py
cloudViewer-0.3.7.data/purelib/cloudViewer/j_visualizer.py
cloudViewer-0.3.7.data/purelib/cloudViewer/cpu/pybind.cp37-win_amd64.pyd
cloudViewer-0.3.7.data/purelib/cloudViewer/ml/__init__.py
cloudViewer-0.3.7.data/purelib/cloudViewer/ml/configs.py
cloudViewer-0.3.7.data/purelib/cloudViewer/ml/datasets.py
cloudViewer-0.3.7.data/purelib/cloudViewer/ml/utils.py
cloudViewer-0.3.7.data/purelib/cloudViewer/ml/vis.py
cloudViewer-0.3.7.data/purelib/cloudViewer/ml/contrib/__init__.py
cloudViewer-0.3.7.data/purelib/cloudViewer/ml/tf/__init__.py
cloudViewer-0.3.7.data/purelib/cloudViewer/ml/tf/configs.py
cloudViewer-0.3.7.data/purelib/cloudViewer/ml/tf/dataloaders.py
cloudViewer-0.3.7.data/purelib/cloudViewer/ml/tf/datasets.py
cloudViewer-0.3.7.data/purelib/cloudViewer/ml/tf/models.py
cloudViewer-0.3.7.data/purelib/cloudViewer/ml/tf/pipelines.py
cloudViewer-0.3.7.data/purelib/cloudViewer/ml/tf/vis.py
cloudViewer-0.3.7.data/purelib/cloudViewer/ml/tf/layers/__init__.py
cloudViewer-0.3.7.data/purelib/cloudViewer/ml/tf/modules/losses.py
cloudViewer-0.3.7.data/purelib/cloudViewer/ml/tf/modules/metrics.py
cloudViewer-0.3.7.data/purelib/cloudViewer/ml/tf/ops/__init__.py
cloudViewer-0.3.7.data/purelib/cloudViewer/ml/tf/python/layers/convolutions.py
cloudViewer-0.3.7.data/purelib/cloudViewer/ml/tf/python/layers/neighbor_search.py
cloudViewer-0.3.7.dist-info/LICENSE.txt
cloudViewer-0.3.7.dist-info/METADATA
cloudViewer-0.3.7.dist-info/WHEEL
cloudViewer-0.3.7.dist-info/top_level.txt
cloudViewer-0.3.7.dist-info/RECORD
