Metadata-Version: 2.1
Name: cloudViewer
Version: 0.3.7
Summary: ['cloudViewer is an open-source library that supports rapid development of software that deals with 3D data.']
Home-page: http://www.erow.cn
Author: cloudViewer Team
Author-email: dahailu@foxmail.com
License: MIT
Project-URL: Documentation, http://www.erow.cn/docs
Project-URL: Source code, https://github.com/Asher-1/ErowCloudViewer
Project-URL: Issues, https://github.com/Asher-1/ErowCloudViewer/issues
Keywords: 3D reconstruction point cloud mesh RGB-D visualization
Platform: UNKNOWN
Classifier: Development Status :: 3 - Alpha
Classifier: Environment :: MacOS X
Classifier: Environment :: Win32 (MS Windows)
Classifier: Environment :: X11 Applications
Classifier: Intended Audience :: Developers
Classifier: Intended Audience :: Education
Classifier: Intended Audience :: Other Audience
Classifier: Intended Audience :: Science/Research
Classifier: License :: OSI Approved :: MIT License
Classifier: Natural Language :: English
Classifier: Operating System :: POSIX :: Linux
Classifier: Programming Language :: C
Classifier: Programming Language :: C++
Classifier: Programming Language :: Python :: 3
Classifier: Programming Language :: Python :: 3.5
Classifier: Programming Language :: Python :: 3.6
Classifier: Programming Language :: Python :: 3.7
Classifier: Programming Language :: Python :: 3.8
Classifier: Topic :: Education
Classifier: Topic :: Multimedia :: Graphics :: 3D Modeling
Classifier: Topic :: Multimedia :: Graphics :: 3D Rendering
Classifier: Topic :: Multimedia :: Graphics :: Capture
Classifier: Topic :: Multimedia :: Graphics :: Graphics Conversion
Classifier: Topic :: Multimedia :: Graphics :: Viewers
Classifier: Topic :: Scientific/Engineering
Classifier: Topic :: Scientific/Engineering :: Mathematics
Classifier: Topic :: Scientific/Engineering :: Visualization
Classifier: Topic :: Software Development :: Libraries :: Python Modules
Classifier: Topic :: Utilities
Requires-Dist: ipywidgets
Requires-Dist: widgetsnbextension
Requires-Dist: notebook
Requires-Dist: numpy
Requires-Dist: matplotlib
